{
  "kind": "collectionType",
  "collectionName": "articles",
  "info": {
    "singularName": "article",
    "pluralName": "articles",
    "displayName": "Article"
  },
  "options": {
    "draftAndPublish": true
  },
  "pluginOptions": {},
  "attributes": {
    "Title": {
      "type": "string"
    },
    "authors": {
      "type": "relation",
      "relation": "manyToMany",
      "target": "api::author.author",
      "inversedBy": "articles"
    },
    "Content": {
      "type": "richtext"
    },
    "code_snippets": {
      "type": "relation",
      "relation": "manyToMany",
      "target": "api::code-snippet.code-snippet",
      "inversedBy": "articles"
    },
    "tags": {
      "type": "relation",
      "relation": "manyToMany",
      "target": "api::tag.tag",
      "inversedBy": "articles"
    },
    "Featured_Image": {
      "type": "component",
      "repeatable": true,
      "component": "media.image"
    }
  }
}
